colorbymood/__init__.py
colorbymood/cli.py
colorbymood/click_utils.py
colorbymood/color.py
colorbymood/color.yaml
colorbymood/frequency.yaml
colorbymood/io.py
colorbymood/window.py
colorbymood-0.3.1.dist-info/METADATA
colorbymood-0.3.1.dist-info/WHEEL
colorbymood-0.3.1.dist-info/entry_points.txt
colorbymood-0.3.1.dist-info/RECORD
