Metadata-Version: 2.1
Name: colorbymood
Version: 0.3.1
Summary: 
Author: Niels Maedern
Author-email: maedern@student.ethz.ch
Requires-Python: >=3.10,<4.0
Classifier: Programming Language :: Python :: 3
Classifier: Programming Language :: Python :: 3.10
Classifier: Programming Language :: Python :: 3.11
Classifier: Programming Language :: Python :: 3.12
Requires-Dist: click (>=8.1.3,<9.0.0)
Requires-Dist: matplotlib (>=3.7.0,<4.0.0)
Requires-Dist: pyqt6 (>=6.4.2,<7.0.0)
Requires-Dist: pytest (>=7.4.3,<8.0.0)
Requires-Dist: pyyaml (>=6.0,<7.0)
